[
    {
        "detail": "Total Turnover Rs:",
        "value": 13162298717.48
    },
    {
        "detail": "Total Traded Shares",
        "value": 30438305.0
    },
    {
        "detail": "Total Transactions",
        "value": 142733.0
    },
    {
        "detail": "Total Scrips Traded",
        "value": 342.0
    },
    {
        "detail": "Total Market Capitalization Rs:",
        "value": 5009383410601.0
    },
    {
        "detail": "Total Float Market Capitalization Rs:",
        "value": 1696448360139.6
    }
]